bmptoduet/__init__.py
bmptoduet/bmptoduet.py
bmptoduet-0.1.3.dist-info/entry_points.txt
bmptoduet-0.1.3.dist-info/LICENSE
bmptoduet-0.1.3.dist-info/WHEEL
bmptoduet-0.1.3.dist-info/METADATA
bmptoduet-0.1.3.dist-info/RECORD
