Metadata-Version: 2.1
Name: bmptoduet
Version: 0.1.3
Summary: Convert Monochrome BMP to Duet3D Menu Image
Home-page: https://github.com/keyz182/bmptoduet
License: MIT
Author: Kieran David Evans
Author-email: keyz182@gmail.com
Requires-Python: >=3.7,<3.11
Classifier: License :: OSI Approved :: MIT License
Classifier: Programming Language :: Python :: 3
Classifier: Programming Language :: Python :: 3.10
Classifier: Programming Language :: Python :: 3.7
Classifier: Programming Language :: Python :: 3.8
Classifier: Programming Language :: Python :: 3.9
Requires-Dist: Pillow (>=8.4.0,<9.0.0)
Requires-Dist: numpy (>=1.21.5,<2.0.0)
Project-URL: Bug Tracker, https://github.com/keyz182/bmptoduet/issues
Project-URL: Repository, https://github.com/keyz182/bmptoduet
